copilotkey/__init__.py
copilotkey-0.2.0.dist-info/licenses/LICENSE
copilotkey-0.2.0.dist-info/METADATA
copilotkey-0.2.0.dist-info/WHEEL
copilotkey-0.2.0.dist-info/top_level.txt
copilotkey-0.2.0.dist-info/RECORD
