Metadata-Version: 2.4
Name: copilotkey
Version: 0.2.0
Summary: Send Shift+Win+F23 (Copilot Key) with one call
Author: Daniel Kramer
Author-email: dvkramer@outlook.com
License: MIT
Classifier: Programming Language :: Python :: 3
Classifier: Operating System :: Microsoft :: Windows
Classifier: License :: OSI Approved :: MIT License
Requires-Python: >=3.8
License-File: LICENSE
Dynamic: license-file
